{
  "project_name": "Real-Time Conservation Monitoring System",
  "completion_date": "2025-08-21T10:50:05.308375",
  "components": {
    "iot_sensors": 25,
    "satellite_coverage": 1120000,
    "anomaly_detection": "Active",
    "alert_system": "Operational",
    "dashboard": "Interactive",
    "validation_score": 66.66666666666667
  },
  "next_steps": [
    "Deploy to production environment",
    "Integrate with conservation management systems",
    "Establish stakeholder alert protocols",
    "Implement data archival and backup systems",
    "Schedule regular system maintenance"
  ]
}